kadego/__init__.py
kadego/bots/__init__.py
kadego/bots/bot.py
kadego/exceptions/__init__.py
kadego/exceptions/invalid_bot_configuration_error.py
kadego/loggers/__init__.py
kadego/loggers/base_logger.py
kadego/loggers/json_file_logger.py
kadego/loggers/logger.py
kadego/loggers/single_level_words_logger.py
kadego/observers/__init__.py
kadego/observers/observer.py
kadego/observers/periodic_observer.py
kadego/observers/progress_bar_observer.py
kadego/observers/status_observer.py
kadego/observers/timeout_observer.py
kadego/runners/__init__.py
kadego/runners/runner.py
kadego/runners/single_level_scrapper.py
kadego/solvers/__init__.py
kadego/solvers/correct_solver.py
kadego/solvers/quit_solver.py
kadego/solvers/skip_solver.py
kadego/solvers/solver.py
kadego/strategies/__init__.py
kadego/strategies/always_correct_strategy.py
kadego/strategies/always_quit_strategy.py
kadego/strategies/curious_strategy.py
kadego/strategies/strategy.py
kadego/utils/__init__.py
kadego/utils/game_status.py
kadego/utils/menu_navigator.py
kadego/utils/playwright.py
kadego/utils/question_outcome.py
kadego/utils/speed.py
kadego/world_maps/__init__.py
kadego/world_maps/kanji_de_go_map.py
kadego/world_maps/world_map.py
kadego-0.1.1.dist-info/LICENSE
kadego-0.1.1.dist-info/METADATA
kadego-0.1.1.dist-info/WHEEL
kadego-0.1.1.dist-info/top_level.txt
kadego-0.1.1.dist-info/RECORD
