Metadata-Version: 2.1
Name: kadego
Version: 0.1.1
Summary: A package to run bots for 漢字でGO!.
Author-email: Moritz Eckert <Moritz.Eckert@web.de>
License:                                  Apache License
Project-URL: Repository, https://github.com/Moritz72/kadego
Project-URL: Bug Tracker, https://github.com/Moritz72/kadego/issues
License-File: LICENSE
Requires-Dist: playwright>=1.49.1
Requires-Dist: tqdm>=4.66.5
